odoo/addons/quality_mitxelena/__init__.py
odoo/addons/quality_mitxelena/__manifest__.py
odoo/addons/quality_mitxelena/models/__init__.py
odoo/addons/quality_mitxelena/models/quality_mitxelena.py
odoo/addons/quality_mitxelena/static/src/img/cilindricidad.png
odoo/addons/quality_mitxelena/static/src/img/circular.png
odoo/addons/quality_mitxelena/static/src/img/concentricidad.png
odoo/addons/quality_mitxelena/static/src/img/formalinea.png
odoo/addons/quality_mitxelena/static/src/img/formasuperficie.png
odoo/addons/quality_mitxelena/static/src/img/inclinacion.png
odoo/addons/quality_mitxelena/static/src/img/paralelismo.png
odoo/addons/quality_mitxelena/static/src/img/perpendicularidad.png
odoo/addons/quality_mitxelena/static/src/img/planicidad.png
odoo/addons/quality_mitxelena/static/src/img/posicion.png
odoo/addons/quality_mitxelena/static/src/img/rectitud.png
odoo/addons/quality_mitxelena/static/src/img/redondez.png
odoo/addons/quality_mitxelena/static/src/img/simetria.png
odoo/addons/quality_mitxelena/static/src/img/total.png
odoo/addons/quality_mitxelena/views/quality_views.xml
odoo14_addon_quality_mitxelena-14.0.0.3.3.dist-info/METADATA
odoo14_addon_quality_mitxelena-14.0.0.3.3.dist-info/WHEEL
odoo14_addon_quality_mitxelena-14.0.0.3.3.dist-info/top_level.txt
odoo14_addon_quality_mitxelena-14.0.0.3.3.dist-info/RECORD
