Metadata-Version: 2.1
Name: odoo14-addon-quality-mitxelena
Version: 14.0.0.3.3
Summary: Quality Mitxelena
Home-page: https://www.talaios.coop
Author: Talaios
License: UNKNOWN
Platform: UNKNOWN
Classifier: Programming Language :: Python
Classifier: Framework :: Odoo
Classifier: Framework :: Odoo :: 14.0
Requires-Python: >=3.6
Requires-Dist: odoo14-addon-quality-control-oca
Requires-Dist: odoo <14.1dev,>=14.0a
